urlinfotessmack-0.2.0.dist-info/METADATA
urlinfotessmack-0.2.0.dist-info/WHEEL
urlinfotessmack-0.2.0.dist-info/entry_points.txt
urlinfotessmack-0.2.0.dist-info/licenses/LICENSE
urlinfotessmack/__init__.py
urlinfotessmack-0.2.0.dist-info/RECORD
